webcookie.py
samlwebcookie-1.0.0.dist-info/LICENSE
samlwebcookie-1.0.0.dist-info/METADATA
samlwebcookie-1.0.0.dist-info/WHEEL
samlwebcookie-1.0.0.dist-info/entry_points.txt
samlwebcookie-1.0.0.dist-info/top_level.txt
samlwebcookie-1.0.0.dist-info/RECORD
