Metadata-Version: 2.1
Name: samlwebcookie
Version: 1.0.0
Summary: UNKNOWN
Home-page: https://cthorne.me
Author: Christopher Thorne
Author-email: UNKNOWN
License: UNKNOWN
Platform: UNKNOWN
Requires-Dist: bs4
Requires-Dist: requests
Requires-Dist: requests-ntlm
